{
  "formatVersion": 1,
  "nodes": [
    {
      "id": "0",
      "name": "Ship",
      "children": [],
      "components": [
        {
          "type": "SpriteRenderer",
          "config": {
            "formatVersion": 1,
            "spriteAssetId": "14",
            "animationId": null,
            "horizontalFlip": false,
            "verticalFlip": false,
            "castShadow": false,
            "receiveShadow": false,
            "color": "ffffff",
            "overrideOpacity": false,
            "opacity": null,
            "materialType": "basic",
            "shaderAssetId": null
          },
          "id": "0"
        },
        {
          "type": "Behavior",
          "config": {
            "behaviorName": "ShipBehavior",
            "propertyValues": {
              "playerNumber": {
                "type": "number",
                "value": 1
              }
            }
          },
          "id": "1"
        },
        {
          "type": "CannonBody",
          "config": {
            "formatVersion": 2,
            "mass": 3,
            "fixedRotation": true,
            "group": 1,
            "mask": 1,
            "shape": "box",
            "positionOffset": {
              "x": 0,
              "y": 0,
              "z": 0
            },
            "orientationOffset": {
              "x": 0,
              "y": 0,
              "z": 0
            },
            "halfSize": {
              "x": 2,
              "y": 3,
              "z": 0.5
            },
            "radius": 1,
            "height": 1,
            "segments": 16
          },
          "id": "3"
        }
      ],
      "position": {
        "x": 0,
        "y": 0,
        "z": 0
      },
      "orientation": {
        "x": 0,
        "y": 0,
        "z": 0,
        "w": 1
      },
      "scale": {
        "x": 1,
        "y": 1,
        "z": 1
      },
      "visible": true,
      "layer": 0,
      "prefab": null
    }
  ]
}